Metadata-Version: 1.0
Name: probdists-udacity-tarciso
Version: 0.1
Summary: Gaussian distributions
Home-page: UNKNOWN
Author: Tarciso Braz
Author-email: tarciso.filho@ccc.ufcg.edu.br
License: UNKNOWN
Platform: UNKNOWN
